api.py
config.py
core/__init__.py
core/decay.py
core/device.py
core/entities.py
core/profile.py
core/search.py
memory_mori-0.1.3.dist-info/licenses/LICENSE
stores/__init__.py
stores/profile_store.py
stores/vector_store.py
utils/compare_json_results.py
utils/compare_results.py
utils/visualize_results.py
memory_mori-0.1.3.dist-info/METADATA
memory_mori-0.1.3.dist-info/WHEEL
memory_mori-0.1.3.dist-info/top_level.txt
memory_mori-0.1.3.dist-info/RECORD
