Metadata-Version: 2.4
Name: memory-mori
Version: 0.1.3
Summary: Persistent memory for LLMs - Give your AI conversations long-term memory with intelligent context retrieval
Author-email: David Halvarson <your-email@example.com>
License: MIT
Project-URL: Homepage, https://github.com/dhalv/MemoryMori
Project-URL: Repository, https://github.com/dhalv/MemoryMori
Project-URL: Issues, https://github.com/dhalv/MemoryMori/issues
Keywords: ai,memory,embeddings,search,nlp,llm,chatbot,vector-database,rag
Classifier: Development Status :: 4 - Beta
Classifier: Intended Audience :: Developers
Classifier: License :: OSI Approved :: MIT License
Classifier: Programming Language :: Python :: 3
Classifier: Programming Language :: Python :: 3.8
Classifier: Programming Language :: Python :: 3.9
Classifier: Programming Language :: Python :: 3.10
Classifier: Programming Language :: Python :: 3.11
Classifier: Programming Language :: Python :: 3.12
Classifier: Topic :: Software Development :: Libraries :: Python Modules
Classifier: Topic :: Scientific/Engineering :: Artificial Intelligence
Requires-Python: >=3.8
License-File: LICENSE
Requires-Dist: chromadb>=0.4.0
Requires-Dist: sentence-transformers>=2.2.0
Requires-Dist: spacy>=3.5.0
Requires-Dist: rank-bm25>=0.2.2
Requires-Dist: numpy>=1.21.0
Provides-Extra: openai
Requires-Dist: openai>=1.0.0; extra == "openai"
Provides-Extra: dev
Requires-Dist: pytest>=7.0.0; extra == "dev"
Requires-Dist: black>=23.0.0; extra == "dev"
Requires-Dist: ruff>=0.1.0; extra == "dev"
Dynamic: license-file
